{
  "type": "Feature",
  "geometry": {
    "type": "Point",
    "coordinates": [112.415588, -7.120441]
  },
  "properties": {
    "name": "Lamongan"
  }
}https://raw.githubusercontent.com/Shintiad/pa_maps1/master/maps_json/output.geojson?token=GHSAT0AAAAAACWDKV3YL47AK66Y6DBDQG3YZV7ERBQ