{
  "type": "FeatureCollection",
  "features": [
    {
      "type": "Feature",
      "geometry": {
        "type": "Point",
        "coordinates": [112.415588, -7.120441]
      },
      "properties": {
        "name": "Lamongan",
        "admin_level": "5",
        "source": "landsat"
      }
    }
  ]
}
